{
  "_id": "plastic_rubber_measurement_equipment",
  "category": "Plastic & Rubber Machinery",
  "category_code": "3",
  "schema": {
    "bsonType": "object",
    "required": [
      "machine_id",
      "category",
      "subcategory",
      "sub_subcategory",
      "manufacturer",
      "model",
      "year_of_manufacture"
    ],
    "properties": {
      "machine_id": {
        "bsonType": "string"
      },
      "category": {
        "bsonType": "string",
        "enum": [
          "Plastic & Rubber Machinery"
        ]
      },
      "category_code": {
        "bsonType": "string"
      },
      "subcategory": {
        "bsonType": "string",
        "enum": [
          "Quality Assurance Equipment"
        ]
      },
      "subcategory_code": {
        "bsonType": "string"
      },
      "sub_subcategory": {
        "bsonType": "string",
        "enum": [
          "Measurement Equipment"
        ]
      },
      "sub_subcategory_code": {
        "bsonType": "string"
      },
      "manufacturer": {
        "bsonType": "string"
      },
      "model": {
        "bsonType": "string"
      },
      "year_of_manufacture": {
        "bsonType": "int"
      },
      "condition": {
        "bsonType": "string",
        "enum": [
          "New",
          "Used - Excellent",
          "Used - Good",
          "Used - Fair",
          "Refurbished",
          "For Parts"
        ]
      },
      "serial_number": {
        "bsonType": "string"
      },
      "operating_hours": {
        "bsonType": "int"
      },
      "weight": {
        "bsonType": "double"
      },
      "dimensions": {
        "bsonType": "object",
        "properties": {
          "length": {
            "bsonType": "double"
          },
          "width": {
            "bsonType": "double"
          },
          "height": {
            "bsonType": "double"
          }
        }
      },
      "power_supply": {
        "bsonType": "object",
        "properties": {
          "voltage": {
            "bsonType": "int"
          },
          "phase": {
            "bsonType": "int",
            "enum": [
              1,
              3
            ]
          },
          "frequency": {
            "bsonType": "int",
            "enum": [
              50,
              60
            ]
          },
          "consumption": {
            "bsonType": "double"
          }
        }
      },
      "compatibility": {
        "bsonType": "object",
        "properties": {
          "material_types": {
            "bsonType": "array",
            "items": {
              "bsonType": "string"
            }
          },
          "machine_types": {
            "bsonType": "array",
            "items": {
              "bsonType": "string"
            }
          }
        }
      },
      "control_system": {
        "bsonType": "object",
        "properties": {
          "type": {
            "bsonType": "string"
          },
          "interface": {
            "bsonType": "string"
          }
        }
      },
      "measurement_system": {
        "bsonType": "object",
        "properties": {
          "measurement_type": {
            "bsonType": "string"
          },
          "range": {
            "bsonType": "object",
            "properties": {
              "min": {
                "bsonType": "double"
              },
              "max": {
                "bsonType": "double"
              }
            }
          },
          "accuracy": {
            "bsonType": "double"
          },
          "measurement_speed": {
            "bsonType": "double"
          }
        }
      },
      "functions": {
        "bsonType": "array",
        "items": {
          "bsonType": "string"
        },
        "description": "Lists the primary functions of the machine",
        "enum": [
          "Measuring dimensions of plastic or rubber products",
          "Ensuring product specifications compliance",
          "Detecting surface or thickness variations",
          "Supporting quality control processes"
        ]
      },
      "seo_tags": {
        "bsonType": "array",
        "items": {
          "bsonType": "string"
        },
        "description": "SEO-optimized tags for search engine indexing",
        "enum": [
          "plastic measurement equipment",
          "rubber dimension measuring machine",
          "industrial quality measurement",
          "plastic thickness gauge",
          "European measurement equipment"
        ]
      },
      "manufacturers_european": {
        "bsonType": "array",
        "items": {
          "bsonType": "string"
        },
        "description": "Prominent European manufacturers for this machine type",
        "enum": [
          "Mitutoyo (Germany)",
          "Hexagon (Sweden)",
          "Zeiss (Germany)",
          "Mahr (Germany)",
          "Tesa (Switzerland)"
        ]
      },
      "automation_level": {
        "bsonType": "string",
        "enum": [
          "Semi-Automatic",
          "Fully Automatic"
        ]
      },
      "calibration_standard": {
        "bsonType": "string"
      },
      "maintenance_history": {
        "bsonType": "string"
      },
      "known_issues": {
        "bsonType": "string"
      },
      "has_manuals": {
        "bsonType": "bool"
      }
    }
  },
  "sub_subcategory": "Measurement Equipment",
  "sub_subcategory_code": "3.13.1",
  "subcategory": "Quality Assurance Equipment",
  "subcategory_code": "3.13",
  "version": "1.0"
}