{
  "_id": "food_processing_pasta_extruders",
  "category": "Food Processing Machinery",
  "category_code": "5",
  "schema": {
    "bsonType": "object",
    "required": [
      "machine_id",
      "category",
      "subcategory",
      "sub_subcategory",
      "manufacturer",
      "model",
      "year_of_manufacture"
    ],
    "properties": {
      "machine_id": {
        "bsonType": "string"
      },
      "category": {
        "bsonType": "string",
        "enum": [
          "Food Processing Machinery"
        ]
      },
      "category_code": {
        "bsonType": "string"
      },
      "subcategory": {
        "bsonType": "string",
        "enum": [
          "Pasta and Noodle Production"
        ]
      },
      "subcategory_code": {
        "bsonType": "string"
      },
      "sub_subcategory": {
        "bsonType": "string",
        "enum": [
          "Pasta Extruders"
        ]
      },
      "sub_subcategory_code": {
        "bsonType": "string"
      },
      "manufacturer": {
        "bsonType": "string"
      },
      "model": {
        "bsonType": "string"
      },
      "year_of_manufacture": {
        "bsonType": "int"
      },
      "condition": {
        "bsonType": "string",
        "enum": [
          "New",
          "Used - Excellent",
          "Used - Good",
          "Used - Fair",
          "Refurbished",
          "For Parts"
        ]
      },
      "serial_number": {
        "bsonType": "string"
      },
      "operating_hours": {
        "bsonType": "int"
      },
      "weight": {
        "bsonType": "double"
      },
      "dimensions": {
        "bsonType": "object",
        "properties": {
          "length": {
            "bsonType": "double"
          },
          "width": {
            "bsonType": "double"
          },
          "height": {
            "bsonType": "double"
          }
        }
      },
      "power_supply": {
        "bsonType": "object",
        "properties": {
          "voltage": {
            "bsonType": "int"
          },
          "phase": {
            "bsonType": "int",
            "enum": [
              1,
              3
            ]
          },
          "frequency": {
            "bsonType": "int",
            "enum": [
              50,
              60
            ]
          },
          "consumption": {
            "bsonType": "double"
          }
        }
      },
      "processing_capacity": {
        "bsonType": "object",
        "properties": {
          "max_volume": {
            "bsonType": "double"
          },
          "product_types": {
            "bsonType": "array",
            "items": {
              "bsonType": "string"
            }
          }
        }
      },
      "control_system": {
        "bsonType": "object",
        "properties": {
          "type": {
            "bsonType": "string"
          },
          "interface": {
            "bsonType": "string"
          }
        }
      },
      "extrusion_system": {
        "bsonType": "object",
        "properties": {
          "extruder_type": {
            "bsonType": "string"
          },
          "output_rate": {
            "bsonType": "double"
          },
          "die_types": {
            "bsonType": "array",
            "items": {
              "bsonType": "string"
            }
          },
          "pressure_range": {
            "bsonType": "object",
            "properties": {
              "min": {
                "bsonType": "double"
              },
              "max": {
                "bsonType": "double"
              }
            }
          }
        }
      },
      "functions": {
        "bsonType": "array",
        "items": {
          "bsonType": "string"
        },
        "description": "Lists the primary functions of the machine",
        "enum": [
          "Extruding dough into pasta shapes",
          "Producing fresh or dried pasta",
          "Supporting various pasta varieties",
          "Ensuring consistent extrusion quality"
        ]
      },
      "seo_tags": {
        "bsonType": "array",
        "items": {
          "bsonType": "string"
        },
        "description": "SEO-optimized tags for search engine indexing",
        "enum": [
          "pasta extruder machine",
          "industrial pasta maker",
          "pasta production equipment",
          "noodle extruder",
          "European pasta extruders"
        ]
      },
      "manufacturers_european": {
        "bsonType": "array",
        "items": {
          "bsonType": "string"
        },
        "description": "Prominent European manufacturers for this machine type",
        "enum": [
          "Pavan (Italy)",
          "B\u00fchler (Switzerland)",
          "Italpast (Italy)",
          "Landucci (Italy)",
          "Fava (Italy)"
        ]
      },
      "automation_level": {
        "bsonType": "string",
        "enum": [
          "Semi-Automatic",
          "Fully Automatic"
        ]
      },
      "cooling_system": {
        "bsonType": "bool"
      },
      "maintenance_history": {
        "bsonType": "string"
      },
      "known_issues": {
        "bsonType": "string"
      },
      "has_manuals": {
        "bsonType": "bool"
      }
    }
  },
  "sub_subcategory": "Pasta Extruders",
  "sub_subcategory_code": "5.14.1",
  "subcategory": "Pasta and Noodle Production",
  "subcategory_code": "5.14",
  "version": "1.0"
}