{
  "_id": "food_processing_butter_churns",
  "category": "Food Processing Machinery",
  "category_code": "5",
  "schema": {
    "bsonType": "object",
    "required": [
      "machine_id",
      "category",
      "subcategory",
      "sub_subcategory",
      "manufacturer",
      "model",
      "year_of_manufacture"
    ],
    "properties": {
      "machine_id": {
        "bsonType": "string"
      },
      "category": {
        "bsonType": "string",
        "enum": [
          "Food Processing Machinery"
        ]
      },
      "category_code": {
        "bsonType": "string"
      },
      "subcategory": {
        "bsonType": "string",
        "enum": [
          "Dairy Equipment"
        ]
      },
      "subcategory_code": {
        "bsonType": "string"
      },
      "sub_subcategory": {
        "bsonType": "string",
        "enum": [
          "Butter Churns"
        ]
      },
      "sub_subcategory_code": {
        "bsonType": "string"
      },
      "manufacturer": {
        "bsonType": "string"
      },
      "model": {
        "bsonType": "string"
      },
      "year_of_manufacture": {
        "bsonType": "int"
      },
      "condition": {
        "bsonType": "string",
        "enum": [
          "New",
          "Used - Excellent",
          "Used - Good",
          "Used - Fair",
          "Refurbished",
          "For Parts"
        ]
      },
      "serial_number": {
        "bsonType": "string"
      },
      "operating_hours": {
        "bsonType": "int"
      },
      "weight": {
        "bsonType": "double"
      },
      "dimensions": {
        "bsonType": "object",
        "properties": {
          "length": {
            "bsonType": "double"
          },
          "width": {
            "bsonType": "double"
          },
          "height": {
            "bsonType": "double"
          }
        }
      },
      "power_supply": {
        "bsonType": "object",
        "properties": {
          "voltage": {
            "bsonType": "int"
          },
          "phase": {
            "bsonType": "int",
            "enum": [
              1,
              3
            ]
          },
          "frequency": {
            "bsonType": "int",
            "enum": [
              50,
              60
            ]
          },
          "consumption": {
            "bsonType": "double"
          }
        }
      },
      "processing_capacity": {
        "bsonType": "object",
        "properties": {
          "max_volume": {
            "bsonType": "double"
          },
          "product_types": {
            "bsonType": "array",
            "items": {
              "bsonType": "string"
            }
          }
        }
      },
      "control_system": {
        "bsonType": "object",
        "properties": {
          "type": {
            "bsonType": "string"
          },
          "interface": {
            "bsonType": "string"
          }
        }
      },
      "churning_system": {
        "bsonType": "object",
        "properties": {
          "churn_type": {
            "bsonType": "string"
          },
          "capacity": {
            "bsonType": "double"
          },
          "churning_speed": {
            "bsonType": "double"
          },
          "temperature_control": {
            "bsonType": "bool"
          }
        }
      },
      "functions": {
        "bsonType": "array",
        "items": {
          "bsonType": "string"
        },
        "description": "Lists the primary functions of the machine",
        "enum": [
          "Churning cream into butter",
          "Producing consistent butter quality",
          "Supporting small to large-scale operations",
          "Separating butter from buttermilk"
        ]
      },
      "seo_tags": {
        "bsonType": "array",
        "items": {
          "bsonType": "string"
        },
        "description": "SEO-optimized tags for search engine indexing",
        "enum": [
          "butter churn machine",
          "industrial butter churner",
          "dairy butter equipment",
          "butter making machinery",
          "European butter churns"
        ]
      },
      "manufacturers_european": {
        "bsonType": "array",
        "items": {
          "bsonType": "string"
        },
        "description": "Prominent European manufacturers for this machine type",
        "enum": [
          "GEA (Germany)",
          "Alfa Laval (Sweden)",
          "Tetra Pak (Sweden)",
          "Fasa (Lithuania)",
          "Simon Fr\u00e8res (France)"
        ]
      },
      "automation_level": {
        "bsonType": "string",
        "enum": [
          "Semi-Automatic",
          "Fully Automatic"
        ]
      },
      "hygiene_features": {
        "bsonType": "array",
        "items": {
          "bsonType": "string"
        }
      },
      "maintenance_history": {
        "bsonType": "string"
      },
      "known_issues": {
        "bsonType": "string"
      },
      "has_manuals": {
        "bsonType": "bool"
      }
    }
  },
  "sub_subcategory": "Butter Churns",
  "sub_subcategory_code": "5.4.4",
  "subcategory": "Dairy Equipment",
  "subcategory_code": "5.4",
  "version": "1.0"
}